r00logger/__init__.py
r00logger/core.py
r00logger/test.py
r00logger/test2.py
r00logger/helpers/__init__.py
r00logger/helpers/constants.py
r00logger-0.1.5.dist-info/METADATA
r00logger-0.1.5.dist-info/WHEEL
r00logger-0.1.5.dist-info/RECORD
