Metadata-Version: 2.4
Name: r00logger
Version: 0.1.5
Requires-Python: >=3.10
Requires-Dist: decohints
Requires-Dist: loguru
